{
    "plants":[
        {
            "name": "succulent",
            "description": "my succulent",
            "image": "/images/t-241g-m9b_1.jpg"
        },
        {
            "name": "ficus",
            "description": "my ficus",
            "image": "/images/t-241g-m9b_1.jpg"
        },
        {
            "name": "ficus",
            "description": "my ficus",
            "image": "/images/t-241g-m9b_1.jpg"
        },
        {
            "name": "succulent",
            "description": "my succulent",
            "image": "/images/t-241g-m9b_1.jpg"
        },
        {
            "name": "ficus",
            "description": "my ficus",
            "image": "/images/t-241g-m9b_1.jpg"
        },
        {
            "name": "ficus",
            "description": "my ficus",
            "image": "/images/t-241g-m9b_1.jpg"
        }
    ]
}